setup.cfg
setup.py
async_signal/__init__.py
async_signal/exceptions.py
async_signal/signals.py
async_signal/utils.py
async_signal.egg-info/PKG-INFO
async_signal.egg-info/SOURCES.txt
async_signal.egg-info/dependency_links.txt
async_signal.egg-info/not-zip-safe
async_signal.egg-info/requires.txt
async_signal.egg-info/top_level.txt
tests/__init__.py
tests/test_connect.py
tests/test_dispatch.py
tests/test_has_receivers.py