Metadata-Version: 1.1
Name: async-signal
Version: 0.1.1
Summary: Create signals to use with asyncio coroutines
Home-page: https://github.com/Tiago-Lira/async-signal
Author: Tiago Lira
Author-email: tiagoliradsantos@gmail.com
License: UNKNOWN
Download-URL: https://github.com/Tiago-Lira/async-signal/tarball/0.1.1
Keywords: asyncio,signals,python3,dispatch,async,coroutines
Platform: UNKNOWN
